ad_api/__init__.py
ad_api/version.py
ad_api/api/__init__.py
ad_api/api/account.py
ad_api/api/advertising_test_account.py
ad_api/api/attribution.py
ad_api/api/audiences.py
ad_api/api/billing.py
ad_api/api/brand_metrics.py
ad_api/api/creative_assets.py
ad_api/api/eligibility.py
ad_api/api/exports.py
ad_api/api/history.py
ad_api/api/insights.py
ad_api/api/invoices.py
ad_api/api/localization.py
ad_api/api/manager_accounts.py
ad_api/api/metadata.py
ad_api/api/portfolios.py
ad_api/api/portfolios_v3.py
ad_api/api/profiles.py
ad_api/api/recommendations.py
ad_api/api/reports.py
ad_api/api/stores.py
ad_api/api/stream.py
ad_api/api/validation_configurations.py
ad_api/api/dsp/__init__.py
ad_api/api/dsp/access_token_client.py
ad_api/api/dsp/client.py
ad_api/api/dsp/credential_provider.py
ad_api/api/dsp/reports.py
ad_api/api/sb/__init__.py
ad_api/api/sb/ad_creatives_v4.py
ad_api/api/sb/ad_groups.py
ad_api/api/sb/ad_groups_v4.py
ad_api/api/sb/ads_v4.py
ad_api/api/sb/benchmarks.py
ad_api/api/sb/bid_recommendations.py
ad_api/api/sb/brands.py
ad_api/api/sb/campaigns.py
ad_api/api/sb/campaigns_v4.py
ad_api/api/sb/forecast.py
ad_api/api/sb/keywords.py
ad_api/api/sb/keywords_recommendations.py
ad_api/api/sb/landing_page_asins.py
ad_api/api/sb/media.py
ad_api/api/sb/moderation.py
ad_api/api/sb/negative_keywords.py
ad_api/api/sb/negative_product_targeting.py
ad_api/api/sb/product_targeting.py
ad_api/api/sb/recommendations.py
ad_api/api/sb/reports.py
ad_api/api/sb/snapshots.py
ad_api/api/sb/stores.py
ad_api/api/sb/targeting_recommendations.py
ad_api/api/sb/themes.py
ad_api/api/sd/__init__.py
ad_api/api/sd/ad_groups.py
ad_api/api/sd/bid_recommendations.py
ad_api/api/sd/brand_safety.py
ad_api/api/sd/budget_rules.py
ad_api/api/sd/campaigns.py
ad_api/api/sd/campaigns_budget_usage.py
ad_api/api/sd/creatives.py
ad_api/api/sd/forecast.py
ad_api/api/sd/negative_product_targeting.py
ad_api/api/sd/product_ads.py
ad_api/api/sd/product_targeting.py
ad_api/api/sd/recommendations.py
python_amazon_ad_api-0.6.8.dist-info/licenses/LICENSE
python_amazon_ad_api-0.6.8.dist-info/METADATA
python_amazon_ad_api-0.6.8.dist-info/WHEEL
python_amazon_ad_api-0.6.8.dist-info/top_level.txt
python_amazon_ad_api-0.6.8.dist-info/RECORD
