Metadata-Version: 2.4
Name: python-amazon-ad-api
Version: 0.6.8
Summary: Python wrapper for the Amazon Advertising API
Home-page: https://github.com/denisneuf/python-amazon-ad-api
Author: Daniel Alvaro
Author-email: denisneuf@hotmail.com
License: MIT
Project-URL: Bug Tracker, https://github.com/denisneuf/python-amazon-ad-api/issues
Classifier: Programming Language :: Python :: 3
Classifier: License :: OSI Approved :: MIT License
Classifier: Operating System :: OS Independent
License-File: LICENSE
Requires-Dist: requests<2.33.0,>=2.27.1
Requires-Dist: six<1.18,>=1.16
Requires-Dist: cachetools<6.3,>=5.0
Requires-Dist: pycryptodome<3.24,>=3.13
Requires-Dist: pytz<2026.0,>=2021.3
Requires-Dist: confuse<2.2,>=1.7
Dynamic: author
Dynamic: author-email
Dynamic: home-page
Dynamic: license
Dynamic: license-file
Dynamic: requires-dist
Dynamic: summary
